short/short.py
short_cli-1.0.dist-info/METADATA
short_cli-1.0.dist-info/WHEEL
short_cli-1.0.dist-info/top_level.txt
short_cli-1.0.dist-info/RECORD
