Metadata-Version: 2.1
Name: short-cli
Version: 1.0
Summary: Shorten and track URLs from the command line
Home-page: http://github.com/Clocktapus/short-cli
Author: Max Beyer
Author-email: mwbpenguin@gmail.com
License: MIT
Platform: UNKNOWN
Requires-Dist: bs4
Requires-Dist: requests
